civitai/creators.py
civitai/images.py
civitai/models.py
civitai/tags.py
civitai/utils.py
civitai-1.0.0.dist-info/LICENSE
civitai-1.0.0.dist-info/METADATA
civitai-1.0.0.dist-info/WHEEL
civitai-1.0.0.dist-info/top_level.txt
civitai-1.0.0.dist-info/RECORD
